widip/__init__.py
widip/__main__.py
widip/composing.py
widip/files.py
widip/loader.py
widip/test_files.py
widip/test_loader.py
widip/watch.py
widip/widish.py
widip-0.1.0.dist-info/METADATA
widip-0.1.0.dist-info/WHEEL
widip-0.1.0.dist-info/licenses/LICENSE
widip-0.1.0.dist-info/RECORD
