Metadata-Version: 2.4
Name: widip
Version: 0.1.0
Summary: Widip is an interactive environment for computing with wiring diagrams in modern systems
Project-URL: Source, https://github.com/colltoaction/widip
License-File: LICENSE
Requires-Dist: discopy>=1.2.1
Requires-Dist: nx-yaml==0.3.0
Requires-Dist: pyyaml>=6.0.1
Requires-Dist: watchdog>=4.0.1
